{
    "name": "Consultancy_Assignments",
    "doctype": "DocType",
    "fields": [
        {
            "fieldname": "Title",
            "label": "Project Title",
            "fieldtype": "Data"
        },
        {
            "fieldname": "A_Code",
            "label": "Project Code",
            "fieldtype": "Data"
        },
        {
            "fieldname": "Stage",
            "label": "Project Stage",
            "fieldtype": "Link",
            "options": "Stages"
        },
        {
            "fieldname": "Priority",
            "label": "Priority",
            "fieldtype": "Data"
        },
        {
            "fieldname": "Client",
            "label": "Client",
            "fieldtype": "Link",
            "options": "Clients"
        },
        {
            "fieldname": "Funder",
            "label": "Funder",
            "fieldtype": "Data"
        },
        {
            "fieldname": "ContractRef",
            "label": "Contract Reference",
            "fieldtype": "Data"
        },
        {
            "fieldname": "Status",
            "label": "Status",
            "fieldtype": "Data"
        },
        {
            "fieldname": "LeadConsultant",
            "label": "Lead Consultant",
            "fieldtype": "Link",
            "options": "Consultants"
        },
        {
            "fieldname": "Sector",
            "label": "Sector",
            "fieldtype": "Link",
            "options": "Sectors"
        },
        {
            "fieldname": "ServiceLine",
            "label": "Service Line",
            "fieldtype": "Link",
            "options": "ServiceLines"
        },
        {
            "fieldname": "Country",
            "label": "Country",
            "fieldtype": "Link",
            "options": "Countries"
        },
        {
            "fieldname": "Governorate",
            "label": "Governorate",
            "fieldtype": "Link",
            "options": "Governorates"
        },
        {
            "fieldname": "City",
            "label": "City",
            "fieldtype": "Data"
        },
        {
            "fieldname": "StartDate",
            "label": "Start Date",
            "fieldtype": "Date"
        },
        {
            "fieldname": "EndDate",
            "label": "End Date",
            "fieldtype": "Date"
        },
        {
            "fieldname": "TotalContractValue",
            "label": "Total Contract Value",
            "fieldtype": "Currency"
        },
        {
            "fieldname": "SignatoryName",
            "label": "Authorized Signatory",
            "fieldtype": "Data"
        },
        {
            "fieldname": "BillingContact",
            "label": "Billing Contact",
            "fieldtype": "Data"
        },
        {
            "fieldname": "PaymentTerms",
            "label": "Payment Terms",
            "fieldtype": "Select",
            "options": [
                "Net 15",
                "Net 30",
                "Net 60",
                "Milestone Based"
            ]
        },
        {
            "fieldname": "Objectives",
            "label": "Project Objectives",
            "fieldtype": "Text Area"
        },
        {
            "fieldname": "Scope_In",
            "label": "Scope: Included",
            "fieldtype": "Text Area"
        },
        {
            "fieldname": "Scope_Out",
            "label": "Scope: Excluded",
            "fieldtype": "Text Area"
        },
        {
            "fieldname": "Signed_Contract",
            "label": "Signed Contract (PDF)",
            "fieldtype": "Attach"
        }
    ]
}